<?xml version="1.0" encoding="UTF-8"?>
<text xmlns:xsi="http://www.w3.org/2001/XMLSchema-instance" xsi:noNamespaceSchemaLocation="../../meta/schema.xsd">

<sentence>
  <token value="Про" lemma="про" tags="prep" />
  <token value="це" lemma="це" tags="noun:inanim:n:v_zna:pron:dem" />
  <token value="," lemma="," tags="punct" />
  <token value="зокрема" lemma="зокрема" tags="adv" />
  <token value="," lemma="," tags="punct" />
  <token value="йшлося" lemma="йтися" tags="verb:rev:imperf:past:n" />
  <token value="на" lemma="на" tags="prep" />
  <token value="розширеній" lemma="розширений" tags="adj:f:v_mis:adjp:pasv:perf" />
  <token value="Колегії" lemma="колегія" tags="noun:inanim:f:v_mis" />
  <token value="Управління" lemma="управління" tags="noun:inanim:n:v_rod" />
  <token value="Державної" lemma="державний" tags="adj:f:v_rod" />
  <token value="міграційної" lemma="міграційний" tags="adj:f:v_rod" />
  <token value="служби" lemma="служба" tags="noun:inanim:f:v_rod" />
  <token value="України" lemma="Україна" tags="noun:inanim:f:v_rod:prop:geo" />
  <token value="в" lemma="в" tags="prep" />
  <token value="Київській" lemma="київський" tags="adj:f:v_mis" />
  <token value="області" lemma="область" tags="noun:inanim:f:v_mis" />
  <token value="," lemma="," tags="punct" />
  <token value="яка" lemma="який" tags="adj:f:v_naz:pron:int:rel:def" />
  <token value="відбулася" lemma="відбутися" tags="verb:rev:perf:past:f" />
  <token value="26" lemma="26" tags="number" />
  <token value="липня" lemma="липень" tags="noun:inanim:m:v_rod" />
  <token value="у" lemma="у" tags="prep" />
  <token value="місті" lemma="місто" tags="noun:inanim:n:v_mis" />
  <token value="Вишгороді" lemma="Вишгород" tags="noun:inanim:m:v_mis:prop:geo" />
  <token value="за" lemma="за" tags="prep" />
  <token value="участю" lemma="участь" tags="noun:inanim:f:v_oru" />
  <token value="Голови" lemma="голова" tags="noun:anim:m:v_rod" />
  <token value="ДМС" lemma="ДМС" tags="noun:inanim:f:v_rod:nv:abbr:prop" />
  <token value="України" lemma="Україна" tags="noun:inanim:f:v_rod:prop:geo" />
  <token value="Максима" lemma="Максим" tags="noun:anim:m:v_rod:prop:fname" />
  <token value="Соколюка" lemma="Соколюк" tags="noun:anim:m:v_rod:prop:lname" />
  <token value="." lemma="." tags="punct" />
</sentence>
<paragraph/>

<sentence>
  <token value="Голова" lemma="голова" tags="noun:anim:m:v_naz" />
  <token value="акцентував" lemma="акцентувати" tags="verb:imperf:past:m" />
  <token value="увагу" lemma="увага" tags="noun:inanim:f:v_zna" />
  <token value="колег" lemma="колега" tags="noun:anim:p:v_rod" />
  <token value="на" lemma="на" tags="prep" />
  <token value="безумовному" lemma="безумовний" tags="adj:n:v_mis" />
  <token value="дотриманні" lemma="дотримання" tags="noun:inanim:n:v_mis" />
  <token value="вимог" lemma="вимога" tags="noun:inanim:p:v_rod" />
  <token value="законодавства" lemma="законодавство" tags="noun:inanim:n:v_rod" />
  <token value="під" lemma="під" tags="prep" />
  <token value="час" lemma="час" tags="noun:inanim:m:v_zna" />
  <token value="надання" lemma="надання" tags="noun:inanim:n:v_rod" />
  <token value="громадянам" lemma="громадянин" tags="noun:anim:p:v_dav" />
  <token value="адміністративних" lemma="адміністративний" tags="adj:p:v_rod" />
  <token value="послуг" lemma="послуга" tags="noun:inanim:p:v_rod" />
  <token value="," lemma="," tags="punct" />
  <token value="наголосивши" lemma="наголосивши" tags="advp:perf" />
  <token value="на" lemma="на" tags="prep" />
  <token value="забезпеченні" lemma="забезпечення" tags="noun:inanim:n:v_mis" />
  <token value="суворого" lemma="суворий" tags="adj:n:v_rod:compb" />
  <token value="дотримання" lemma="дотримання" tags="noun:inanim:n:v_rod" />
  <token value="законодавства" lemma="законодавство" tags="noun:inanim:n:v_rod" />
  <token value="при" lemma="при" tags="prep" />
  <token value="прийнятті" lemma="прийняття" tags="noun:inanim:n:v_mis" />
  <token value="рішень" lemma="рішення" tags="noun:inanim:p:v_rod" />
  <token value="та" lemma="та" tags="conj:coord" />
  <token value="неприпустимості" lemma="неприпустимість" tags="noun:inanim:f:v_rod" />
  <token value="вимагання" lemma="вимагання" tags="noun:inanim:n:v_rod" />
  <token value="непередбачених" lemma="непередбачений" tags="adj:p:v_rod" />
  <token value="законодавством" lemma="законодавство" tags="noun:inanim:n:v_oru" />
  <token value="документів" lemma="документ" tags="noun:inanim:p:v_rod" />
  <token value="." lemma="." tags="punct" />
</sentence>
<paragraph/>

<sentence>
  <token value="Окрему" lemma="окремий" tags="adj:f:v_zna" />
  <token value="увагу" lemma="увага" tags="noun:inanim:f:v_zna" />
  <token value="Максим" lemma="Максим" tags="noun:anim:m:v_naz:prop:fname" />
  <token value="Соколюк" lemma="Соколюк" tags="noun:anim:m:v_naz:prop:lname" />
  <token value="приділив" lemma="приділити" tags="verb:perf:past:m" />
  <token value="питанням" lemma="питання" tags="noun:inanim:p:v_dav" />
  <token value="протидії" lemma="протидія" tags="noun:inanim:f:v_rod" />
  <token value="корупції" lemma="корупція" tags="noun:inanim:f:v_dav" />
  <token value="та" lemma="та" tags="conj:coord" />
  <token value="зазначив" lemma="зазначити" tags="verb:perf:past:m:xp1" />
  <token value="," lemma="," tags="punct" />
  <token value="що" lemma="що" tags="conj:subord" />
  <token value="Державна" lemma="державний" tags="adj:f:v_naz" />
  <token value="міграційна" lemma="міграційний" tags="adj:f:v_naz" />
  <token value="служба" lemma="служба" tags="noun:inanim:f:v_naz" />
  <token value="України" lemma="Україна" tags="noun:inanim:f:v_rod:prop:geo" />
  <token value="зацікавлена" lemma="зацікавлений" tags="adj:f:v_naz:adjp:pasv:perf:compb" />
  <token value="в" lemma="в" tags="prep" />
  <token value="прозорому" lemma="прозорий" tags="adj:n:v_mis:compb" />
  <token value="наданні" lemma="надання" tags="noun:inanim:n:v_mis" />
  <token value="послуг" lemma="послуга" tags="noun:inanim:p:v_rod" />
  <token value="населенню" lemma="населення" tags="noun:inanim:n:v_dav" />
  <token value="та" lemma="та" tags="conj:coord" />
  <token value="унеможливленні" lemma="унеможливлення" tags="noun:inanim:n:v_mis" />
  <token value="існування" lemma="існування" tags="noun:inanim:n:v_rod" />
  <token value="корупційної" lemma="корупційний" tags="adj:f:v_rod:compb" />
  <token value="складової" lemma="складова" tags="noun:inanim:f:v_rod" />
  <token value="." lemma="." tags="punct" />
</sentence>
<paragraph/>

<sentence>
  <token value="Також" lemma="також" tags="adv" />
  <token value="під" lemma="під" tags="prep" />
  <token value="час" lemma="час" tags="noun:inanim:m:v_zna" />
  <token value="робочої" lemma="робочий" tags="adj:f:v_rod" />
  <token value="зустрічі" lemma="зустріч" tags="noun:inanim:f:v_rod" />
  <token value="," lemma="," tags="punct" />
  <token value="у" lemma="у" tags="prep" />
  <token value="якій" lemma="який" tags="adj:f:v_mis:pron:int:rel:def" />
  <token value="взяли" lemma="взяти" tags="verb:perf:past:p" />
  <token value="участь" lemma="участь" tags="noun:inanim:f:v_zna" />
  <token value="начальник" lemma="начальник" tags="noun:anim:m:v_naz" />
  <token value="Управління" lemma="управління" tags="noun:inanim:n:v_rod" />
  <token value="ДМС" lemma="ДМС" tags="noun:inanim:f:v_rod:nv:abbr:prop" />
  <token value="України" lemma="Україна" tags="noun:inanim:f:v_rod:prop:geo" />
  <token value="Київщини" lemma="Київщина" tags="noun:inanim:f:v_rod:prop:geo" />
  <token value="Олексій" lemma="Олексій" tags="noun:anim:m:v_naz:prop:fname" />
  <token value="Пустовіт" lemma="Пустовіт" tags="noun:anim:m:v_naz:prop:lname" />
  <token value="та" lemma="та" tags="conj:coord" />
  <token value="керівники" lemma="керівник" tags="noun:anim:p:v_naz" />
  <token value="територіальних" lemma="територіальний" tags="adj:p:v_rod" />
  <token value="і" lemma="і" tags="conj:coord" />
  <token value="структурних" lemma="структурний" tags="adj:p:v_rod" />
  <token value="підрозділів" lemma="підрозділ" tags="noun:inanim:p:v_rod" />
  <token value="," lemma="," tags="punct" />
  <token value="було" lemma="бути" tags="verb:imperf:past:n:insert" />
  <token value="підсумовано" lemma="підсумувати" tags="verb:perf:impers" />
  <token value="результати" lemma="результат" tags="noun:inanim:p:v_zna" />
  <token value="роботи" lemma="робота" tags="noun:inanim:f:v_rod" />
  <token value="Управління" lemma="управління" tags="noun:inanim:n:v_rod" />
  <token value="протягом" lemma="протягом" tags="prep" />
  <token value="першого" lemma="перший" tags="adj:n:v_rod:numr" />
  <token value="півріччя" lemma="півріччя" tags="noun:inanim:n:v_rod" />
  <token value="2018" lemma="2018" tags="number" />
  <token value="року" lemma="рік" tags="noun:inanim:m:v_rod" />
  <token value="." lemma="." tags="punct" />
</sentence>
<paragraph/>

<sentence>
  <token value="Зокрема" lemma="зокрема" tags="adv" />
  <token value="," lemma="," tags="punct" />
  <token value="у" lemma="у" tags="prep" />
  <token value="звітний" lemma="звітний" tags="adj:m:v_zna:rinanim" />
  <token value="період" lemma="період" tags="noun:inanim:m:v_zna" />
  <token value="працівники" lemma="працівник" tags="noun:anim:p:v_naz" />
  <token value="територіальних" lemma="територіальний" tags="adj:p:v_rod" />
  <token value="підрозділів" lemma="підрозділ" tags="noun:inanim:p:v_rod" />
  <token value="області" lemma="область" tags="noun:inanim:f:v_rod" />
  <token value="оформили" lemma="оформити" tags="verb:perf:past:p" />
  <token value="майже" lemma="майже" tags="adv" />
  <token value="30" lemma="30" tags="number" />
  <token value="тисяч" lemma="тисяча" tags="noun:inanim:p:v_rod:numr" />
  <token value="паспортів" lemma="паспорт" tags="noun:inanim:p:v_rod" />
  <token value="громадянина" lemma="громадянин" tags="noun:anim:m:v_rod" />
  <token value="України" lemma="Україна" tags="noun:inanim:f:v_rod:prop:geo" />
  <token value="(" lemma="(" tags="punct" />
  <token value="ID-картка" lemma="ID-картка" tags="noun:inanim:f:v_naz" />
  <token value=")" lemma=")" tags="punct" />
  <token value="," lemma="," tags="punct" />
  <token value="понад" lemma="понад" tags="prep" />
  <token value="140" lemma="140" tags="number" />
  <token value="тисяч" lemma="тисяча" tags="noun:inanim:p:v_rod:numr" />
  <token value="паспортів" lemma="паспорт" tags="noun:inanim:p:v_rod" />
  <token value="громадянина" lemma="громадянин" tags="noun:anim:m:v_rod" />
  <token value="України" lemma="Україна" tags="noun:inanim:f:v_rod:prop:geo" />
  <token value="для" lemma="для" tags="prep" />
  <token value="виїзду" lemma="виїзд" tags="noun:inanim:m:v_rod" />
  <token value="за" lemma="за" tags="prep" />
  <token value="кордон" lemma="кордон" tags="noun:inanim:m:v_zna" />
  <token value="та" lemma="та" tags="conj:coord" />
  <token value="близько" lemma="близько" tags="prep" />
  <token value="900" lemma="900" tags="number" />
  <token value="посвідок" lemma="посвідка" tags="noun:inanim:p:v_rod" />
  <token value="на" lemma="на" tags="prep" />
  <token value="постійне" lemma="постійний" tags="adj:n:v_zna:compb" />
  <token value="проживання" lemma="проживання" tags="noun:inanim:n:v_zna" />
  <token value="в" lemma="в" tags="prep" />
  <token value="Україні" lemma="Україна" tags="noun:inanim:f:v_mis:prop:geo" />
  <token value="." lemma="." tags="punct" />
</sentence>
<sentence>
  <token value="Від" lemma="від" tags="prep" />
  <token value="іноземних" lemma="іноземний" tags="adj:p:v_rod" />
  <token value="громадян" lemma="громадянин" tags="noun:anim:p:v_rod" />
  <token value="та" lemma="та" tags="conj:coord" />
  <token value="осіб" lemma="особа" tags="noun:anim:p:v_rod" />
  <token value="без" lemma="без" tags="prep" />
  <token value="громадянства" lemma="громадянство" tags="noun:inanim:n:v_rod" />
  <token value="було" lemma="бути" tags="verb:imperf:past:n:insert" />
  <token value="прийнято" lemma="прийняти" tags="verb:perf:impers" />
  <token value="до" lemma="до" tags="prep" />
  <token value="розгляду" lemma="розгляд" tags="noun:inanim:m:v_rod" />
  <token value="близько" lemma="близько" tags="prep" />
  <token value="600" lemma="600" tags="number" />
  <token value="клопотань" lemma="клопотання" tags="noun:inanim:p:v_rod" />
  <token value="про" lemma="про" tags="prep" />
  <token value="отримання" lemma="отримання" tags="noun:inanim:n:v_zna" />
  <token value="дозволу" lemma="дозвіл" tags="noun:inanim:m:v_rod" />
  <token value="на" lemma="на" tags="prep" />
  <token value="імміграцію" lemma="імміграція" tags="noun:inanim:f:v_zna" />
  <token value="," lemma="," tags="punct" />
  <token value="понад" lemma="понад" tags="prep" />
  <token value="500" lemma="500" tags="number" />
  <token value="–" lemma="–" tags="punct" />
  <token value="на" lemma="на" tags="prep" />
  <token value="імміграцію" lemma="імміграція" tags="noun:inanim:f:v_zna" />
  <token value="," lemma="," tags="punct" />
  <token value="а" lemma="а" tags="conj:coord" />
  <token value="також" lemma="також" tags="adv" />
  <token value="оформлено" lemma="оформити" tags="verb:perf:impers" />
  <token value="понад" lemma="понад" tags="prep" />
  <token value="тисячу" lemma="тисяча" tags="noun:inanim:f:v_zna:numr" />
  <token value="посвідок" lemma="посвідка" tags="noun:inanim:p:v_rod" />
  <token value="на" lemma="на" tags="prep" />
  <token value="тимчасове" lemma="тимчасовий" tags="adj:n:v_zna" />
  <token value="проживання" lemma="проживання" tags="noun:inanim:n:v_zna" />
  <token value="." lemma="." tags="punct" />
</sentence>
<paragraph/>

<sentence>
  <token value="Крім" lemma="крім" tags="prep" />
  <token value="того" lemma="те" tags="noun:inanim:n:v_rod:pron:dem" />
  <token value="," lemma="," tags="punct" />
  <token value="з" lemma="з" tags="prep" />
  <token value="початку" lemma="початок" tags="noun:inanim:m:v_rod:xp2" />
  <token value="року" lemma="рік" tags="noun:inanim:m:v_rod" />
  <token value="на" lemma="на" tags="prep" />
  <token value="території" lemma="територія" tags="noun:inanim:f:v_mis" />
  <token value="Київської" lemma="київський" tags="adj:f:v_rod" />
  <token value="області" lemma="область" tags="noun:inanim:f:v_rod" />
  <token value="виявили" lemma="виявити" tags="verb:perf:past:p" />
  <token value="понад" lemma="понад" tags="prep" />
  <token value="300" lemma="300" tags="number" />
  <token value="нелегальних" lemma="нелегальний" tags="adj:p:v_rod" />
  <token value="мігрантів" lemma="мігрант" tags="noun:anim:p:v_rod" />
  <token value="." lemma="." tags="punct" />
</sentence>

</text>
