<?xml version="1.0" encoding="UTF-8"?>
<text>
<sentence>
  <token value="Використовуючи" lemma="використовуючи" tags="advp:imperf" />
  <token value="препарат" lemma="препарат" tags="noun:inanim:m:v_zna" />
  <token value="," lemma="," tags="punct" />
  <token value="здатний" lemma="здатний" tags="adj:m:v_naz" />
  <token value="поліпшити" lemma="поліпшити" tags="verb:perf:inf" />
  <token value="здоров'я" lemma="здоров'я" tags="noun:inanim:n:v_zna" />
  <token value="кишківника" lemma="кишківник" tags="noun:inanim:m:v_rod" />
  <token value="птиці" lemma="птиця" tags="noun:inanim:f:v_rod" />
  <token value="," lemma="," tags="punct" />
  <token value="можна" lemma="можна" tags="noninfl:&amp;predic" />
  <token value="уникнути" lemma="уникнути" tags="verb:perf:inf" />
  <token value="погіршення" lemma="погіршення" tags="noun:inanim:n:v_rod" />
  <token value="стану" lemma="стан" tags="noun:inanim:m:v_rod:xp2" />
  <token value="підстилки" lemma="підстилка" tags="noun:inanim:f:v_rod" />
  <token value="і" lemma="і" tags="conj:coord" />
  <token value="," lemma="," tags="punct" />
  <token value="відповідно" lemma="відповідно" tags="adv:compb" />
  <token value="," lemma="," tags="punct" />
  <token value="падіння" lemma="падіння" tags="noun:inanim:n:v_rod" />
  <token value="продуктивності" lemma="продуктивність" tags="noun:inanim:f:v_rod" />
  <token value="бройлерів" lemma="бройлер" tags="noun:anim:p:v_rod" />
  <token value="." lemma="." tags="punct" />
</sentence>
<paragraph/>
<sentence>
  <token value="Виробництво" lemma="виробництво" tags="noun:inanim:n:v_naz" />
  <token value="бройлерів" lemma="бройлер" tags="noun:anim:p:v_rod" />
  <token value="традиційно" lemma="традиційно" tags="adv:compb" />
  <token value="асоціюється" lemma="асоціюватися" tags="verb:rev:imperf:pres:s:3" />
  <token value="з" lemma="з" tags="prep" />
  <token value="якісними" lemma="якісний" tags="adj:p:v_oru:compb" />
  <token value="молодняком" lemma="молодняк" tags="noun:inanim:m:v_oru" />
  <token value="," lemma="," tags="punct" />
  <token value="годівлею" lemma="годівля" tags="noun:inanim:f:v_oru" />
  <token value="," lemma="," tags="punct" />
  <token value="менеджментом" lemma="менеджмент" tags="noun:inanim:m:v_oru" />
  <token value="." lemma="." tags="punct" />
</sentence>
<sentence>
  <token value="Однак" lemma="однак" tags="adv:&amp;insert" />
  <token value="значно" lemma="значно" tags="adv:compb" />
  <token value="менше" lemma="менше" tags="adv:compc:&amp;predic" />
  <token value="уваги" lemma="увага" tags="noun:inanim:f:v_rod" />
  <token value="приділяється" lemma="приділятися" tags="verb:rev:imperf:pres:s:3" />
  <token value="підстилці" lemma="підстилка" tags="noun:inanim:f:v_dav" />
  <token value="," lemma="," tags="punct" />
  <token value="в" lemma="в" tags="prep" />
  <token value="той" lemma="той" tags="adj:m:v_zna:rinanim:&amp;pron:dem" />
  <token value="час" lemma="час" tags="noun:inanim:m:v_zna" />
  <token value="як" lemma="як" tags="part" />
  <token value="вона" lemma="вона" tags="noun:unanim:f:v_naz:&amp;pron:pers:3" />
  <token value="відіграє" lemma="відігравати" tags="verb:imperf:pres:s:3" />
  <token value="величезну" lemma="величезний" tags="adj:f:v_zna" />
  <token value="роль" lemma="роль" tags="noun:inanim:f:v_zna" />
  <token value="у" lemma="у" tags="prep" />
  <token value="процесі" lemma="процес" tags="noun:inanim:m:v_mis" />
  <token value="вирощування" lemma="вирощування" tags="noun:inanim:n:v_rod" />
  <token value="птиці" lemma="птиця" tags="noun:inanim:f:v_rod" />
  <token value="." lemma="." tags="punct" />
</sentence>
<sentence>
  <token value="Часто" lemma="часто" tags="adv:compb" />
  <token value="підстилка" lemma="підстилка" tags="noun:inanim:f:v_naz" />
  <token value="змішується" lemma="змішуватися" tags="verb:rev:imperf:pres:s:3" />
  <token value="з" lemma="з" tags="prep" />
  <token value="різними" lemma="різний" tags="adj:p:v_oru:compb" />
  <token value="залишками" lemma="залишок" tags="noun:inanim:p:v_oru" />
  <token value="корму" lemma="корм" tags="noun:inanim:m:v_rod" />
  <token value="," lemma="," tags="punct" />
  <token value="водою" lemma="вода" tags="noun:inanim:f:v_oru" />
  <token value="," lemma="," tags="punct" />
  <token value="фекаліями" lemma="фекалії" tags="noun:inanim:p:v_oru:ns" />
  <token value="," lemma="," tags="punct" />
  <token value="пір'ям" lemma="пір'я" tags="noun:inanim:n:v_oru" />
  <token value="." lemma="." tags="punct" />
</sentence>
<paragraph/>
<sentence>
  <token value="Якісна" lemma="якісний" tags="adj:f:v_naz:compb" />
  <token value="підстилка" lemma="підстилка" tags="noun:inanim:f:v_naz" />
  <token value="поглинає" lemma="поглинати" tags="verb:imperf:pres:s:3" />
  <token value="надлишки" lemma="надлишок" tags="noun:inanim:p:v_zna" />
  <token value="вологи" lemma="волога" tags="noun:inanim:f:v_rod" />
  <token value="," lemma="," tags="punct" />
  <token value="розбавляє" lemma="розбавляти" tags="verb:imperf:pres:s:3" />
  <token value="фекалії" lemma="фекалії" tags="noun:inanim:p:v_zna:ns" />
  <token value="та" lemma="та" tags="conj:coord" />
  <token value="захищає" lemma="захищати" tags="verb:imperf:pres:s:3" />
  <token value="курчат" lemma="курча" tags="noun:anim:p:v_zna" />
  <token value="від" lemma="від" tags="prep" />
  <token value="холодної" lemma="холодний" tags="adj:f:v_rod:compb" />
  <token value="підлоги" lemma="підлога" tags="noun:inanim:f:v_rod" />
  <token value="." lemma="." tags="punct" />
</sentence>
<sentence>
  <token value="Оптимальна" lemma="оптимальний" tags="adj:f:v_naz:compb" />
  <token value="вологість" lemma="вологість" tags="noun:inanim:f:v_naz" />
  <token value="підстилки" lemma="підстилка" tags="noun:inanim:f:v_rod" />
  <token value="має" lemma="мати" tags="verb:imperf:pres:s:3" />
  <token value="становити" lemma="становити" tags="verb:imperf:inf" />
  <token value="25–35%" lemma="25–35%" tags="number" />
  <token value="." lemma="." tags="punct" />
</sentence>
<sentence>
  <token value="Термін" lemma="термін" tags="noun:inanim:m:v_naz:xp2" />
  <token value="«" lemma="«" tags="punct" />
  <token value="волога" lemma="волога" tags="noun:inanim:f:v_naz" />
  <token value="»" lemma="»" tags="punct" />
  <token value="застосовується" lemma="застосовуватися" tags="verb:rev:imperf:pres:s:3" />
  <token value="щодо" lemma="щодо" tags="prep" />
  <token value="підстилки" lemma="підстилка" tags="noun:inanim:f:v_rod" />
  <token value="," lemma="," tags="punct" />
  <token value="у" lemma="у" tags="prep" />
  <token value="яку" lemma="який" tags="adj:f:v_zna:&amp;pron:int:rel:def" />
  <token value="вбирається" lemma="вбиратися" tags="verb:rev:imperf:pres:s:3" />
  <token value="більше" lemma="більше" tags="adv:compc" />
  <token value="води" lemma="вода" tags="noun:inanim:f:v_rod" />
  <token value="," lemma="," tags="punct" />
  <token value="ніж" lemma="ніж" tags="conj:subord" />
  <token value="випаровується" lemma="випаровуватися" tags="verb:rev:imperf:pres:s:3" />
  <token value="." lemma="." tags="punct" />
</sentence>
<sentence>
  <token value="У" lemma="у" tags="prep" />
  <token value="деяких" lemma="деякий" tags="adj:p:v_mis:&amp;pron:ind" />
  <token value="випадках" lemma="випадок" tags="noun:inanim:p:v_mis" />
  <token value="підстилка" lemma="підстилка" tags="noun:inanim:f:v_naz" />
  <token value="може" lemma="могти" tags="verb:imperf:pres:s:3:&amp;insert" />
  <token value="«" lemma="«" tags="punct" />
  <token value="склеюватися" lemma="склеюватися" tags="verb:rev:imperf:inf" />
  <token value="»" lemma="»" tags="punct" />
  <token value="," lemma="," tags="punct" />
  <token value="тоді" lemma="тоді" tags="adv:&amp;pron:dem" />
  <token value="птиця" lemma="птиця" tags="noun:inanim:f:v_naz" />
  <token value="росте" lemma="рости" tags="verb:imperf:pres:s:3" />
  <token value="на" lemma="на" tags="prep" />
  <token value="сирій" lemma="сирий" tags="adj:f:v_mis:compb" />
  <token value="," lemma="," tags="punct" />
  <token value="слизькій" lemma="слизький" tags="adj:f:v_mis:compb" />
  <token value="і" lemma="і" tags="conj:coord" />
  <token value="липкій" lemma="липкий" tags="adj:f:v_mis" />
  <token value="поверхні" lemma="поверхня" tags="noun:inanim:f:v_mis" />
  <token value="," lemma="," tags="punct" />
  <token value="яка" lemma="який" tags="adj:f:v_naz:&amp;pron:int:rel:def" />
  <token value="є" lemma="бути" tags="verb:imperf:pres:s:3" />
  <token value="резервуаром" lemma="резервуар" tags="noun:inanim:m:v_oru" />
  <token value="для" lemma="для" tags="prep" />
  <token value="розвитку" lemma="розвиток" tags="noun:inanim:m:v_rod" />
  <token value="патогенних" lemma="патогенний" tags="adj:p:v_rod" />
  <token value="мікроорганізмів" lemma="мікроорганізм" tags="noun:inanim:p:v_rod" />
  <token value="." lemma="." tags="punct" />
</sentence>
<sentence>
  <token value="Ба" lemma="ба" tags="conj:subord" />
  <token value="більше" lemma="більше" tags="adv:compc" />
  <token value="," lemma="," tags="punct" />
  <token value="така" lemma="такий" tags="adj:f:v_naz:&amp;pron:dem" />
  <token value="підстилка" lemma="підстилка" tags="noun:inanim:f:v_naz" />
  <token value="призводить" lemma="призводити" tags="verb:imperf:pres:s:3" />
  <token value="до" lemma="до" tags="prep" />
  <token value="підвищення" lemma="підвищення" tags="noun:inanim:n:v_rod" />
  <token value="рівня" lemma="рівень" tags="noun:inanim:m:v_rod" />
  <token value="комах" lemma="комаха" tags="noun:anim:p:v_rod" />
  <token value="," lemma="," tags="punct" />
  <token value="неприємного" lemma="неприємне" tags="noun:inanim:n:v_rod" />
  <token value="запаху" lemma="запах" tags="noun:inanim:m:v_rod" />
  <token value="(" lemma="(" tags="punct" />
  <token value="аміаку" lemma="аміак" tags="noun:inanim:m:v_rod" />
  <token value=")" lemma=")" tags="punct" />
  <token value="," lemma="," tags="punct" />
  <token value="брудного" lemma="брудний" tags="adj:n:v_rod:compb" />
  <token value="пір'я" lemma="пір'я" tags="noun:inanim:n:v_rod" />
  <token value="," lemma="," tags="punct" />
  <token value="пошкодження" lemma="пошкодження" tags="noun:inanim:n:v_rod" />
  <token value="подушечок" lemma="подушечка" tags="noun:inanim:p:v_rod" />
  <token value="лап" lemma="лапа" tags="noun:inanim:p:v_rod" />
  <token value="," lemma="," tags="punct" />
  <token value="серозних" lemma="серозний" tags="adj:p:v_rod" />
  <token value="набряків" lemma="набряк" tags="noun:inanim:p:v_rod" />
  <token value="." lemma="." tags="punct" />
</sentence>
<sentence>
  <token value="згідно" lemma="згідно" tags="adv:compb" />
  <token value="з" lemma="з" tags="prep" />
  <token value="даними" lemma="дані" tags="noun:inanim:p:v_oru:ns" />
  <token value="Хермансеталя" lemma="Хермансеталь" tags="noun:inanim:m:v_rod:prop" />
  <token value="(" lemma="(" tags="punct" />
  <token value="Hermansetal" lemma="Hermansetal" tags="unclass" />
  <token value="," lemma="," tags="punct" />
  <token value="2006" lemma="2006" tags="number" />
  <token value=")" lemma=")" tags="punct" />
  <token value="," lemma="," tags="punct" />
  <token value="під" lemma="під" tags="prep" />
  <token value="час" lemma="час" tags="noun:inanim:m:v_zna" />
  <token value="виробництва" lemma="виробництво" tags="noun:inanim:n:v_rod" />
  <token value="бройлерів" lemma="бройлер" tags="noun:anim:p:v_rod" />
  <token value="втрати" lemma="втрата" tags="noun:inanim:p:v_naz" />
  <token value="через" lemma="через" tags="prep" />
  <token value="поганий" lemma="поганий" tags="adj:m:v_zna:rinanim:compb" />
  <token value="стан" lemma="стан" tags="noun:inanim:m:v_zna:xp2" />
  <token value="підстилки" lemma="підстилка" tags="noun:inanim:f:v_rod" />
  <token value="можуть" lemma="могти" tags="verb:imperf:pres:p:3" />
  <token value="становити" lemma="становити" tags="verb:imperf:inf" />
  <token value="близько" lemma="близько" tags="adv:compb" />
  <token value="950" lemma="950" tags="number" />
  <token value="дол." lemma="дол." tags="noun:inanim:p:v_rod:nv:abbr" />
  <token value="на" lemma="на" tags="prep" />
  <token value="пташник" lemma="пташник" tags="noun:inanim:m:v_zna" />
  <token value="(" lemma="(" tags="punct" />
  <token value="20" lemma="20" tags="number" />
  <token value="тис." lemma="тис." tags="numr:p:v_rod:nv:abbr" />
  <token value="голів" lemma="голова" tags="noun:inanim:p:v_rod" />
  <token value="птиці" lemma="птиця" tags="noun:inanim:f:v_rod" />
  <token value=")" lemma=")" tags="punct" />
  <token value="." lemma="." tags="punct" />
</sentence>
<paragraph/>
<sentence>
  <token value="Чинники" lemma="чинник" tags="noun:inanim:p:v_naz" />
  <token value="," lemma="," tags="punct" />
  <token value="що" lemma="що" tags="conj:subord" />
  <token value="впливають" lemma="впливати" tags="verb:imperf:pres:p:3" />
  <token value="на" lemma="на" tags="prep" />
  <token value="вологу" lemma="вологий" tags="adj:f:v_zna:compb" />
  <token value="підстилку" lemma="підстилка" tags="noun:inanim:f:v_zna" />
</sentence>
<paragraph/>
<sentence>
  <token value="Одразу" lemma="одразу" tags="adv" />
  <token value="кілька" lemma="кілька" tags="numr:p:v_naz:&amp;pron:ind" />
  <token value="чинників" lemma="чинник" tags="noun:inanim:p:v_rod" />
  <token value="впливають" lemma="впливати" tags="verb:imperf:pres:p:3" />
  <token value="на" lemma="на" tags="prep" />
  <token value="якість" lemma="якість" tags="noun:inanim:f:v_zna" />
  <token value="підстилки" lemma="підстилка" tags="noun:inanim:f:v_rod" />
  <token value="." lemma="." tags="punct" />
</sentence>
<sentence>
  <token value="Під" lemma="під" tags="prep" />
  <token value="час" lemma="час" tags="noun:inanim:m:v_zna" />
  <token value="вирощування" lemma="вирощування" tags="noun:inanim:n:v_rod" />
  <token value="бройлерів" lemma="бройлер" tags="noun:anim:p:v_rod" />
  <token value="на" lemma="на" tags="prep" />
  <token value="споживання" lemma="споживання" tags="noun:inanim:n:v_zna" />
  <token value="й" lemma="й" tags="conj:coord" />
  <token value="виведення" lemma="виведення" tags="noun:inanim:n:v_zna" />
  <token value="води" lemma="вода" tags="noun:inanim:f:v_rod" />
  <token value="впливає" lemma="впливати" tags="verb:imperf:pres:s:3" />
  <token value="температура" lemma="температура" tags="noun:inanim:f:v_naz" />
  <token value="та" lemma="та" tags="conj:coord" />
  <token value="вологість" lemma="вологість" tags="noun:inanim:f:v_naz" />
  <token value="у" lemma="у" tags="prep" />
  <token value="приміщенні" lemma="приміщення" tags="noun:inanim:n:v_mis" />
  <token value="." lemma="." tags="punct" />
</sentence>
<sentence>
  <token value="За" lemma="за" tags="prep" />
  <token value="нормальних" lemma="нормальний" tags="adj:p:v_rod:compb" />
  <token value="умов" lemma="умова" tags="noun:inanim:p:v_rod" />
  <token value="споживання" lemma="споживання" tags="noun:inanim:n:v_rod" />
  <token value="води" lemma="вода" tags="noun:inanim:f:v_rod" />
  <token value="птицею" lemma="птиця" tags="noun:inanim:f:v_oru" />
  <token value="буде" lemma="бути" tags="verb:imperf:futr:s:3" />
  <token value="в" lemma="в" tags="prep" />
  <token value="1,75–2" lemma="1,75–2" tags="number" />
  <token value="рази" lemma="раз" tags="noun:inanim:p:v_zna" />
  <token value="вище" lemma="вищий" tags="adj:n:v_naz:compc" />
  <token value="за" lemma="за" tags="prep" />
  <token value="споживання" lemma="споживання" tags="noun:inanim:n:v_zna" />
  <token value="корму" lemma="корм" tags="noun:inanim:m:v_rod" />
  <token value="." lemma="." tags="punct" />
</sentence>
<sentence>
  <token value="В" lemma="в" tags="prep" />
  <token value="умовах" lemma="умова" tags="noun:inanim:p:v_mis" />
  <token value="пташника" lemma="пташник" tags="noun:inanim:m:v_rod" />
  <token value="," lemma="," tags="punct" />
  <token value="розрахованого" lemma="розрахований" tags="adj:m:v_rod:&amp;adjp:pasv:perf" />
  <token value="на" lemma="на" tags="prep" />
  <token value="20" lemma="20" tags="number" />
  <token value="тис." lemma="тис." tags="numr:p:v_rod:nv:abbr" />
  <token value="птиці" lemma="птиця" tags="noun:inanim:f:v_rod" />
  <token value="і" lemma="і" tags="conj:coord" />
  <token value="34" lemma="34" tags="number" />
  <token value="кг" lemma="кг" tags="noun:inanim:p:v_naz:nv:abbr" />
  <token value="птиці" lemma="птиця" tags="noun:inanim:f:v_rod" />
  <token value="/" lemma="/" tags="punct" />
  <token value="м²" lemma="м²" tags="noninfl" />
  <token value="," lemma="," tags="punct" />
  <token value="щодня" lemma="щодня" tags="adv" />
  <token value="в" lemma="в" tags="prep" />
  <token value="підстилку" lemma="підстилка" tags="noun:inanim:f:v_zna" />
  <token value="потрапляє" lemma="потрапляти" tags="verb:imperf:pres:s:3" />
  <token value="до" lemma="до" tags="prep" />
  <token value="2,5" lemma="2,5" tags="number" />
  <token value="т" lemma="т" tags="noun:inanim:p:v_rod:nv:abbr" />
  <token value="води" lemma="вода" tags="noun:inanim:f:v_rod" />
  <token value="." lemma="." tags="punct" />
</sentence>
<paragraph/>
<sentence>
  <token value="Надмірне" lemma="надмірний" tags="adj:n:v_naz" />
  <token value="споживання" lemma="споживання" tags="noun:inanim:n:v_naz" />
  <token value="калію" lemma="калій" tags="noun:inanim:m:v_rod" />
  <token value="," lemma="," tags="punct" />
  <token value="натрію" lemma="натрій" tags="noun:inanim:m:v_rod" />
  <token value="," lemma="," tags="punct" />
  <token value="магнію" lemma="магній" tags="noun:inanim:m:v_rod" />
  <token value="," lemma="," tags="punct" />
  <token value="сульфату" lemma="сульфат" tags="noun:inanim:m:v_rod" />
  <token value="й" lemma="й" tags="conj:coord" />
  <token value="хлору" lemma="хлор" tags="noun:inanim:m:v_rod" />
  <token value="збільшує" lemma="збільшувати" tags="verb:imperf:pres:s:3" />
  <token value="споживання" lemma="споживання" tags="noun:inanim:n:v_zna" />
  <token value="птицею" lemma="птиця" tags="noun:inanim:f:v_oru" />
  <token value="води" lemma="вода" tags="noun:inanim:f:v_rod" />
  <token value="й" lemma="й" tags="conj:coord" />
  <token value="," lemma="," tags="punct" />
  <token value="відповідно" lemma="відповідно" tags="adv:compb" />
  <token value="," lemma="," tags="punct" />
  <token value="виведення" lemma="виведення" tags="noun:inanim:n:v_rod" />
  <token value="її" lemma="вона" tags="noun:unanim:f:v_rod:&amp;pron:pers:3" />
  <token value="з" lemma="з" tags="prep" />
  <token value="організму" lemma="організм" tags="noun:inanim:m:v_rod" />
  <token value="." lemma="." tags="punct" />
</sentence>
<sentence>
  <token value="В" lemma="в" tags="prep" />
  <token value="разі" lemma="раз" tags="noun:inanim:m:v_mis" />
  <token value="проблеми" lemma="проблема" tags="noun:inanim:f:v_rod" />
  <token value="з" lemma="з" tags="prep" />
  <token value="вологою" lemma="вологий" tags="adj:f:v_oru:compb" />
  <token value="підстилкою" lemma="підстилка" tags="noun:inanim:f:v_oru" />
  <token value="насамперед" lemma="насамперед" tags="adv" />
  <token value="треба" lemma="треба" tags="noninfl:&amp;predic" />
  <token value="перевірити" lemma="перевірити" tags="verb:perf:inf" />
  <token value="рівень" lemma="рівень" tags="noun:inanim:m:v_zna" />
  <token value="додавання" lemma="додавання" tags="noun:inanim:n:v_rod" />
  <token value="до" lemma="до" tags="prep" />
  <token value="раціону" lemma="раціон" tags="noun:inanim:m:v_rod" />
  <token value="саме" lemma="саме" tags="part" />
  <token value="цих" lemma="цей" tags="adj:p:v_rod:&amp;pron:dem" />
  <token value="поживних" lemma="поживний" tags="adj:p:v_rod:compb" />
  <token value="речовин" lemma="речовина" tags="noun:inanim:p:v_rod" />
  <token value="." lemma="." tags="punct" />
</sentence>
<paragraph/>
<sentence>
  <token value="Далі" lemma="далі" tags="adv:compc:&amp;predic" />
  <token value="—" lemma="—" tags="punct" />
  <token value="перевірити" lemma="перевірити" tags="verb:perf:inf" />
  <token value="якість" lemma="якість" tags="noun:inanim:f:v_zna" />
  <token value="жиру" lemma="жир" tags="noun:inanim:m:v_rod" />
  <token value="." lemma="." tags="punct" />
</sentence>
<sentence>
  <token value="Жир" lemma="жир" tags="noun:inanim:m:v_naz" />
  <token value="низької" lemma="низький" tags="adj:f:v_rod:compb" />
  <token value="якості" lemma="якість" tags="noun:inanim:f:v_rod" />
  <token value="може" lemma="могти" tags="verb:imperf:pres:s:3:&amp;insert" />
  <token value="сприяти" lemma="сприяти" tags="verb:imperf:inf" />
  <token value="формуванню" lemma="формування" tags="noun:inanim:n:v_dav" />
  <token value="рідких" lemma="рідкий" tags="adj:p:v_rod:compb" />
  <token value="екскрементів" lemma="екскремент" tags="noun:inanim:p:v_rod" />
  <token value="." lemma="." tags="punct" />
</sentence>
<sentence>
  <token value="Окрім" lemma="окрім" tags="prep" />
  <token value="того" lemma="те" tags="noun:inanim:n:v_rod:&amp;pron:dem" />
  <token value="," lemma="," tags="punct" />
  <token value="важливо" lemma="важливо" tags="adv:compb:&amp;predic" />
  <token value="уважно" lemma="уважно" tags="adv:compb" />
  <token value="підійти" lemma="підійти" tags="verb:perf:inf" />
  <token value="до" lemma="до" tags="prep" />
  <token value="підбору" lemma="підбір" tags="noun:inanim:m:v_rod" />
  <token value="компонентів" lemma="компонент" tags="noun:inanim:p:v_rod" />
  <token value="раціону" lemma="раціон" tags="noun:inanim:m:v_rod" />
  <token value="." lemma="." tags="punct" />
</sentence>
<sentence>
  <token value="До" lemma="до" tags="prep" />
  <token value="складу" lemma="склад" tags="noun:inanim:m:v_rod" />
  <token value="пшениці" lemma="пшениця" tags="noun:inanim:f:v_rod" />
  <token value="," lemma="," tags="punct" />
  <token value="ячменю" lemma="ячмінь" tags="noun:inanim:m:v_rod:xp2" />
  <token value="й" lemma="й" tags="conj:coord" />
  <token value="жита" lemma="жито" tags="noun:inanim:n:v_rod" />
  <token value="входить" lemma="входити" tags="verb:imperf:pres:s:3" />
  <token value="велика" lemma="великий" tags="adj:f:v_naz:compb" />
  <token value="кількість" lemma="кількість" tags="noun:inanim:f:v_naz" />
  <token value="некрохмалистих" lemma="некрохмалистий" tags="adj:p:v_rod" />
  <token value="полісахаридів" lemma="полісахарид" tags="noun:inanim:p:v_rod" />
  <token value="." lemma="." tags="punct" />
</sentence>
<sentence>
  <token value="У" lemma="у" tags="prep" />
  <token value="раціони" lemma="раціон" tags="noun:inanim:p:v_zna" />
  <token value="з" lemma="з" tags="prep" />
  <token value="великим" lemma="великий" tags="adj:n:v_oru:compb" />
  <token value="умістом" lemma="уміст" tags="noun:inanim:m:v_oru" />
  <token value="таких" lemma="такий" tags="adj:p:v_rod:&amp;pron:dem" />
  <token value="компонентів" lemma="компонент" tags="noun:inanim:p:v_rod" />
  <token value="рекомендується" lemma="рекомендуватися" tags="verb:rev:imperf:pres:s:3" />
  <token value="додавати" lemma="додавати" tags="verb:imperf:inf" />
  <token value="ферменти" lemma="фермент" tags="noun:inanim:p:v_zna" />
  <token value="для" lemma="для" tags="prep" />
  <token value="запобігання" lemma="запобігання" tags="noun:inanim:n:v_rod" />
  <token value="появи" lemma="поява" tags="noun:inanim:f:v_rod" />
  <token value="мокрої" lemma="мокрий" tags="adj:f:v_rod:compb" />
  <token value="підстилки" lemma="підстилка" tags="noun:inanim:f:v_rod" />
  <token value="." lemma="." tags="punct" />
</sentence>
<sentence>
  <token value="І" lemma="і" tags="part" />
  <token value="нарешті" lemma="нарешті" tags="adv:&amp;insert" />
  <token value="," lemma="," tags="punct" />
  <token value="запліснявілий" lemma="запліснявілий" tags="adj:m:v_naz:&amp;adjp:actv:perf" />
  <token value="корм" lemma="корм" tags="noun:inanim:m:v_naz" />
  <token value="може" lemma="могти" tags="verb:imperf:pres:s:3:&amp;insert" />
  <token value="містити" lemma="містити" tags="verb:imperf:inf" />
  <token value="величезну" lemma="величезний" tags="adj:f:v_zna" />
  <token value="кількість" lemma="кількість" tags="noun:inanim:f:v_zna" />
  <token value="мікотоксинів" lemma="мікотоксин" tags="noun:inanim:p:v_rod" />
  <token value="," lemma="," tags="punct" />
  <token value="які" lemma="який" tags="adj:p:v_naz:&amp;pron:int:rel:def" />
  <token value="," lemma="," tags="punct" />
  <token value="у" lemma="у" tags="prep" />
  <token value="свою" lemma="свій" tags="adj:f:v_zna:&amp;pron:pos" />
  <token value="чергу" lemma="черга" tags="noun:inanim:f:v_zna" />
  <token value="," lemma="," tags="punct" />
  <token value="полюбляють" lemma="полюбляти" tags="verb:imperf:pres:p:3" />
  <token value="вологу" lemma="волога" tags="noun:inanim:f:v_zna" />
  <token value="підстилку" lemma="підстилка" tags="noun:inanim:f:v_zna" />
  <token value="," lemma="," tags="punct" />
  <token value="тому" lemma="тому" tags="adv" />
  <token value="птицю" lemma="птиця" tags="noun:inanim:f:v_zna" />
  <token value="слід" lemma="слід" tags="noninfl:&amp;predic" />
  <token value="годувати" lemma="годувати" tags="verb:imperf:inf" />
  <token value="тільки" lemma="тільки" tags="part" />
  <token value="високоякісними" lemma="високоякісний" tags="adj:p:v_oru:compb" />
  <token value="кормами" lemma="корм" tags="noun:inanim:p:v_oru" />
  <token value="." lemma="." tags="punct" />
</sentence>
<paragraph/>
<sentence>
  <token value="Здоровий" lemma="здоровий" tags="adj:m:v_naz:compb" />
  <token value="кишківник" lemma="кишківник" tags="noun:inanim:m:v_naz" />
  <token value="—" lemma="—" tags="punct" />
  <token value="запорука" lemma="запорука" tags="noun:inanim:f:v_naz" />
  <token value="високої" lemma="високий" tags="adj:f:v_rod:compb" />
  <token value="продуктивності" lemma="продуктивність" tags="noun:inanim:f:v_rod" />
  <token value="бройлерів" lemma="бройлер" tags="noun:anim:p:v_rod" />
  <token value="." lemma="." tags="punct" />
</sentence>
<sentence>
  <token value="Будь-які" lemma="будь-який" tags="adj:p:v_naz:&amp;pron:ind" />
  <token value="зміни" lemma="зміна" tags="noun:inanim:p:v_naz" />
  <token value="в" lemma="в" tags="prep" />
  <token value="нормальному" lemma="нормальний" tags="adj:m:v_mis:compb" />
  <token value="середовищі" lemma="середовище" tags="noun:inanim:n:v_mis" />
  <token value="шлунково-кишкового" lemma="шлунково-кишковий" tags="adj:m:v_rod" />
  <token value="тракту" lemma="тракт" tags="noun:inanim:m:v_rod" />
  <token value="птиці" lemma="птиця" tags="noun:inanim:f:v_rod" />
  <token value="прямо" lemma="прямо" tags="adv:compb" />
  <token value="впливають" lemma="впливати" tags="verb:imperf:pres:p:3" />
  <token value="на" lemma="на" tags="prep" />
  <token value="засвоєння" lemma="засвоєння" tags="noun:inanim:n:v_zna" />
  <token value="поживних" lemma="поживний" tags="adj:p:v_rod:compb" />
  <token value="речовин" lemma="речовина" tags="noun:inanim:p:v_rod" />
  <token value="і" lemma="і" tags="conj:coord" />
  <token value="виведення" lemma="виведення" tags="noun:inanim:n:v_zna" />
  <token value="їх" lemma="вони" tags="noun:unanim:p:v_rod:&amp;pron:pers:3" />
  <token value="з" lemma="з" tags="prep" />
  <token value="організму" lemma="організм" tags="noun:inanim:m:v_rod" />
  <token value="." lemma="." tags="punct" />
</sentence>
<sentence>
  <token value="В" lemma="в" tags="prep" />
  <token value="разі" lemma="раз" tags="noun:inanim:m:v_mis" />
  <token value="запалення" lemma="запалення" tags="noun:inanim:n:v_rod" />
  <token value="кишківника" lemma="кишківник" tags="noun:inanim:m:v_rod" />
  <token value="," lemma="," tags="punct" />
  <token value="спричиненого" lemma="спричинений" tags="adj:m:v_rod:&amp;adjp:pasv:perf" />
  <token value="," lemma="," tags="punct" />
  <token value="наприклад" lemma="наприклад" tags="adv:&amp;insert" />
  <token value="," lemma="," tags="punct" />
  <token value="Eimeria" lemma="Eimeria" tags="unclass" />
  <token value="spp." lemma="spp." tags="unclass" />
  <token value="," lemma="," tags="unclass" />
  <token value="E." lemma="E." tags="unclass" />
  <token value="coli" lemma="coli" tags="unclass" />
  <token value="," lemma="," tags="unclass" />
  <token value="Campylobacter" lemma="Campylobacter" tags="unclass" />
  <token value="spp." lemma="spp." tags="unclass" />
  <token value="," lemma="," tags="punct" />
  <token value="у" lemma="у" tags="prep" />
  <token value="ньому" lemma="він" tags="noun:unanim:m:v_mis:&amp;pron:pers:3" />
  <token value="відбуваються" lemma="відбуватися" tags="verb:rev:imperf:pres:p:3" />
  <token value="такі" lemma="такий" tags="adj:p:v_naz:&amp;pron:dem" />
  <token value="зміни" lemma="зміна" tags="noun:inanim:p:v_naz" />
  <token value=":" lemma=":" tags="punct" />
  <token value="•" lemma="•" tags="punct" />
  <token value="збільшується" lemma="збільшуватися" tags="verb:rev:imperf:pres:s:3" />
  <token value="вироблення" lemma="вироблення" tags="noun:inanim:n:v_naz" />
  <token value="слизу" lemma="слиз" tags="noun:inanim:m:v_rod" />
  <token value="," lemma="," tags="punct" />
  <token value="що" lemma="що" tags="noun:inanim:n:v_naz:&amp;pron:int:rel" />
  <token value="," lemma="," tags="punct" />
  <token value="у" lemma="у" tags="prep" />
  <token value="свою" lemma="свій" tags="adj:f:v_zna:&amp;pron:pos" />
  <token value="чергу" lemma="черга" tags="noun:inanim:f:v_zna" />
  <token value="," lemma="," tags="punct" />
  <token value="пришвидшує" lemma="пришвидшувати" tags="verb:imperf:pres:s:3" />
  <token value="проходження" lemma="проходження" tags="noun:inanim:n:v_zna" />
  <token value="корму" lemma="корм" tags="noun:inanim:m:v_rod" />
  <token value=";" lemma=";" tags="punct" />
  <token value="•" lemma="•" tags="punct" />
  <token value="на" lemma="на" tags="prep" />
  <token value="засвоєння" lemma="засвоєння" tags="noun:inanim:n:v_zna" />
  <token value="води" lemma="вода" tags="noun:inanim:f:v_rod" />
  <token value="є" lemma="бути" tags="verb:imperf:pres:s:3" />
  <token value="менше" lemma="менше" tags="adv:compc:&amp;predic" />
  <token value="часу" lemma="час" tags="noun:inanim:m:v_rod" />
  <token value="," lemma="," tags="punct" />
  <token value="а" lemma="а" tags="conj:coord" />
  <token value="вміст" lemma="вміст" tags="noun:inanim:m:v_naz" />
  <token value="води" lemma="вода" tags="noun:inanim:f:v_rod" />
  <token value="в" lemma="в" tags="prep" />
  <token value="екскрементах" lemma="екскремент" tags="noun:inanim:p:v_mis" />
  <token value="збільшується" lemma="збільшуватися" tags="verb:rev:imperf:pres:s:3" />
  <token value="." lemma="." tags="punct" />
</sentence>
<sentence>
  <token value="Поверхня" lemma="поверхня" tags="noun:inanim:f:v_naz" />
  <token value="стінок" lemma="стінка" tags="noun:inanim:p:v_rod" />
  <token value="кишківника" lemma="кишківник" tags="noun:inanim:m:v_rod" />
  <token value="частково" lemma="частково" tags="adv" />
  <token value="руйнується" lemma="руйнуватися" tags="verb:rev:imperf:pres:s:3" />
  <token value="," lemma="," tags="punct" />
  <token value="а" lemma="а" tags="conj:coord" />
  <token value="," lemma="," tags="punct" />
  <token value="отже" lemma="отже" tags="part" />
  <token value=":" lemma=":" tags="punct" />
  <token value="площа" lemma="площа" tags="noun:inanim:f:v_naz" />
  <token value="поверхні" lemma="поверхня" tags="noun:inanim:f:v_rod" />
  <token value="," lemma="," tags="punct" />
  <token value="доступної" lemma="доступний" tags="adj:f:v_rod:compb" />
  <token value="для" lemma="для" tags="prep" />
  <token value="засвоєння" lemma="засвоєння" tags="noun:inanim:n:v_rod" />
  <token value="поживних" lemma="поживний" tags="adj:p:v_rod:compb" />
  <token value="речовин" lemma="речовина" tags="noun:inanim:p:v_rod" />
  <token value="," lemma="," tags="punct" />
  <token value="зменшується" lemma="зменшуватися" tags="verb:rev:imperf:pres:s:3" />
  <token value="," lemma="," tags="punct" />
  <token value="створюються" lemma="створюватися" tags="verb:rev:imperf:pres:p:3" />
  <token value="сприятливі" lemma="сприятливий" tags="adj:p:v_zna:rinanim:compb" />
  <token value="умови" lemma="умова" tags="noun:inanim:p:v_zna" />
  <token value="для" lemma="для" tags="prep" />
  <token value="розмноження" lemma="розмноження" tags="noun:inanim:n:v_rod" />
  <token value="патогенних" lemma="патогенний" tags="adj:p:v_rod" />
  <token value="мікроорганізмів" lemma="мікроорганізм" tags="noun:inanim:p:v_rod" />
  <token value="і" lemma="і" tags="conj:coord" />
  <token value="виникає" lemma="виникати" tags="verb:imperf:pres:s:3" />
  <token value="діарея" lemma="діарея" tags="noun:inanim:f:v_naz" />
  <token value="." lemma="." tags="punct" />
</sentence>
<paragraph/>
<sentence>
  <token value="Як" lemma="як" tags="adv:&amp;pron:int:rel" />
  <token value="поліпшити" lemma="поліпшити" tags="verb:perf:inf" />
  <token value="якість" lemma="якість" tags="noun:inanim:f:v_zna" />
  <token value="підстилки" lemma="підстилка" tags="noun:inanim:f:v_rod" />
</sentence>
<paragraph/>
<sentence>
  <token value="Велике" lemma="великий" tags="adj:n:v_zna:compb" />
  <token value="значення" lemma="значення" tags="noun:inanim:n:v_zna" />
  <token value="має" lemma="мати" tags="verb:imperf:pres:s:3" />
  <token value="якість" lemma="якість" tags="noun:inanim:f:v_naz" />
  <token value="підстилкового" lemma="підстилковий" tags="adj:m:v_rod" />
  <token value="матеріалу" lemma="матеріал" tags="noun:inanim:m:v_rod" />
  <token value="." lemma="." tags="punct" />
</sentence>
<sentence>
  <token value="Для" lemma="для" tags="prep" />
  <token value="цих" lemma="цей" tags="adj:p:v_rod:&amp;pron:dem" />
  <token value="цілей" lemma="ціль" tags="noun:inanim:p:v_rod" />
  <token value="добре" lemma="добре" tags="adv:compb:&amp;predic" />
  <token value="підходять" lemma="підходити" tags="verb:imperf:pres:p:3" />
  <token value="тирса" lemma="тирса" tags="noun:inanim:f:v_naz" />
  <token value="й" lemma="й" tags="conj:coord" />
  <token value="торф" lemma="торф" tags="noun:inanim:m:v_naz" />
  <token value="," lemma="," tags="punct" />
  <token value="також" lemma="також" tags="conj:coord" />
  <token value="можна" lemma="можна" tags="noninfl:&amp;predic" />
  <token value="використовувати" lemma="використовувати" tags="verb:imperf:inf" />
  <token value="подрібнену" lemma="подрібнений" tags="adj:f:v_zna:&amp;adjp:pasv:perf" />
  <token value="солому" lemma="солома" tags="noun:inanim:f:v_zna" />
  <token value="для" lemma="для" tags="prep" />
  <token value="підвищення" lemma="підвищення" tags="noun:inanim:n:v_rod" />
  <token value="вологопоглинальної" lemma="вологопоглинальний" tags="adj:f:v_rod" />
  <token value="здатності" lemma="здатність" tags="noun:inanim:f:v_rod" />
  <token value="підстилки" lemma="підстилка" tags="noun:inanim:f:v_rod" />
  <token value="." lemma="." tags="punct" />
</sentence>
<sentence>
  <token value="По-друге" lemma="по-друге" tags="adv:&amp;insert" />
  <token value="," lemma="," tags="punct" />
  <token value="подача" lemma="подача" tags="noun:inanim:f:v_naz" />
  <token value="води" lemma="вода" tags="noun:inanim:f:v_rod" />
  <token value="в" lemma="в" tags="prep" />
  <token value="системи" lemma="система" tags="noun:inanim:p:v_zna" />
  <token value="напування" lemma="напування" tags="noun:inanim:n:v_rod" />
  <token value="й" lemma="й" tags="conj:coord" />
  <token value="сам" lemma="сам" tags="adj:m:v_naz:&amp;pron:def" />
  <token value="менеджмент" lemma="менеджмент" tags="noun:inanim:m:v_naz" />
  <token value="у" lemma="у" tags="prep" />
  <token value="господарстві" lemma="господарство" tags="noun:inanim:n:v_mis" />
  <token value="." lemma="." tags="punct" />
</sentence>
<sentence>
  <token value="Забиті" lemma="забитий" tags="adj:p:v_naz:&amp;adjp:pasv:perf:compb" />
  <token value="ніпелі" lemma="ніпель" tags="noun:inanim:p:v_naz" />
  <token value="чи" lemma="чи" tags="conj:coord" />
  <token value="такі" lemma="такий" tags="adj:p:v_naz:&amp;pron:dem" />
  <token value="," lemma="," tags="punct" />
  <token value="що" lemma="що" tags="conj:subord" />
  <token value="підтікають" lemma="підтікати" tags="verb:imperf:pres:p:3" />
  <token value="," lemma="," tags="punct" />
  <token value="слід" lemma="слід" tags="noninfl:&amp;predic" />
  <token value="замінити" lemma="замінити" tags="verb:perf:inf" />
  <token value="," lemma="," tags="punct" />
  <token value="щоб" lemma="щоб" tags="conj:subord" />
  <token value="уникнути" lemma="уникнути" tags="verb:perf:inf" />
  <token value="проливання" lemma="проливання" tags="noun:inanim:n:v_rod" />
  <token value="води" lemma="вода" tags="noun:inanim:f:v_rod" />
  <token value="з" lemma="з" tags="prep" />
  <token value="напувалок" lemma="напувалка" tags="noun:inanim:p:v_rod" />
  <token value="." lemma="." tags="punct" />
</sentence>
<sentence>
  <token value="Вони" lemma="вони" tags="noun:unanim:p:v_naz:&amp;pron:pers:3" />
  <token value="обов'язково" lemma="обов'язково" tags="adv:compb" />
  <token value="мають" lemma="мати" tags="verb:imperf:pres:p:3" />
  <token value="бути" lemma="бути" tags="verb:imperf:inf" />
  <token value="відрегульовані" lemma="відрегульований" tags="adj:p:v_naz:&amp;adjp:pasv:perf" />
  <token value="за" lemma="за" tags="prep" />
  <token value="висотою" lemma="висота" tags="noun:inanim:f:v_oru" />
  <token value="птиці" lemma="птиця" tags="noun:inanim:f:v_rod" />
  <token value="." lemma="." tags="punct" />
</sentence>
<sentence>
  <token value="За" lemma="за" tags="prep" />
  <token value="занадто" lemma="занадто" tags="adv" />
  <token value="низького" lemma="низький" tags="adj:n:v_rod:compb" />
  <token value="розташування" lemma="розташування" tags="noun:inanim:n:v_rod" />
  <token value="напувалок" lemma="напувалка" tags="noun:inanim:p:v_rod" />
  <token value="проливається" lemma="проливатися" tags="verb:rev:imperf:pres:s:3" />
  <token value="більше" lemma="більше" tags="adv:compc" />
  <token value="води" lemma="вода" tags="noun:inanim:f:v_rod" />
  <token value="." lemma="." tags="punct" />
</sentence>
<sentence>
  <token value="По-третє" lemma="по-третє" tags="adv:&amp;insert" />
  <token value="," lemma="," tags="punct" />
  <token value="треба" lemma="треба" tags="noninfl:&amp;predic" />
  <token value="контролювати" lemma="контролювати" tags="verb:imperf:inf" />
  <token value="склад" lemma="склад" tags="noun:inanim:m:v_zna" />
  <token value="раціону" lemma="раціон" tags="noun:inanim:m:v_rod" />
  <token value="й" lemma="й" tags="conj:coord" />
  <token value="уміст" lemma="уміст" tags="noun:inanim:m:v_zna" />
  <token value="у" lemma="у" tags="prep" />
  <token value="ньому" lemma="він" tags="noun:unanim:m:v_mis:&amp;pron:pers:3" />
  <token value="мінеральних" lemma="мінеральний" tags="adj:p:v_rod" />
  <token value="речовин" lemma="речовина" tags="noun:inanim:p:v_rod" />
  <token value="," lemma="," tags="punct" />
  <token value="щоб" lemma="щоб" tags="conj:subord" />
  <token value="гарантувати" lemma="гарантувати" tags="verb:perf:inf" />
  <token value="максимальну" lemma="максимальний" tags="adj:f:v_zna" />
  <token value="продуктивність" lemma="продуктивність" tags="noun:inanim:f:v_zna" />
  <token value="птиці" lemma="птиця" tags="noun:inanim:f:v_rod" />
  <token value="." lemma="." tags="punct" />
</sentence>
<sentence>
  <token value="По-четверте" lemma="по-четверте" tags="adv:&amp;insert" />
  <token value="," lemma="," tags="punct" />
  <token value="важливо" lemma="важливо" tags="adv:compb:&amp;predic" />
  <token value="забезпечити" lemma="забезпечити" tags="verb:perf:inf" />
  <token value="максимальне" lemma="максимальний" tags="adj:n:v_zna" />
  <token value="здоров'я" lemma="здоров'я" tags="noun:inanim:n:v_zna" />
  <token value="кишківника" lemma="кишківник" tags="noun:inanim:m:v_rod" />
  <token value="." lemma="." tags="punct" />
</sentence>
<paragraph/>
<sentence>
  <token value="Проведені" lemma="проведений" tags="adj:p:v_naz:&amp;adjp:pasv:perf" />
  <token value="дослідження" lemma="дослідження" tags="noun:inanim:p:v_naz" />
  <token value="вчених" lemma="вчений" tags="noun:anim:p:v_rod" />
  <token value="вказують" lemma="вказувати" tags="verb:imperf:pres:p:3" />
  <token value="на" lemma="на" tags="prep" />
  <token value="позитивний" lemma="позитивний" tags="adj:m:v_zna:rinanim:compb" />
  <token value="вплив" lemma="вплив" tags="noun:inanim:m:v_zna" />
  <token value="на" lemma="на" tags="prep" />
  <token value="якість" lemma="якість" tags="noun:inanim:f:v_zna" />
  <token value="підстилки" lemma="підстилка" tags="noun:inanim:f:v_rod" />
  <token value="кормової" lemma="кормовий" tags="adj:f:v_rod" />
  <token value="добавки" lemma="добавка" tags="noun:inanim:f:v_rod" />
  <token value="Сангровіт" lemma="Сангровіт" tags="noun:inanim:m:v_naz" />
  <token value="." lemma="." tags="punct" />
</sentence>
<sentence>
  <token value="Волога" lemma="вологий" tags="adj:f:v_naz:compb" />
  <token value="підстилка" lemma="підстилка" tags="noun:inanim:f:v_naz" />
  <token value="може" lemma="могти" tags="verb:imperf:pres:s:3:&amp;insert" />
  <token value="призвести" lemma="призвести" tags="verb:perf:inf" />
  <token value="до" lemma="до" tags="prep" />
  <token value="зниження" lemma="зниження" tags="noun:inanim:n:v_rod" />
  <token value="продуктивності" lemma="продуктивність" tags="noun:inanim:f:v_rod" />
  <token value="бройлерів" lemma="бройлер" tags="noun:anim:p:v_rod" />
  <token value="." lemma="." tags="punct" />
</sentence>
<sentence>
  <token value="Як" lemma="як" tags="conj:subord" />
  <token value="наслідок" lemma="наслідок" tags="noun:inanim:m:v_naz" />
  <token value="—" lemma="—" tags="punct" />
  <token value="пошкодження" lemma="пошкодження" tags="noun:inanim:p:v_naz" />
  <token value="ніг" lemma="нога" tags="noun:inanim:p:v_rod" />
  <token value="," lemma="," tags="punct" />
  <token value="намини" lemma="намини" tags="noun:inanim:p:v_naz:ns" />
  <token value="на" lemma="на" tags="prep" />
  <token value="грудках" lemma="грудка" tags="noun:inanim:p:v_mis" />
  <token value="і" lemma="і" tags="conj:coord" />
  <token value="підвищений" lemma="підвищений" tags="adj:m:v_naz:&amp;adjp:pasv:perf" />
  <token value="рівень" lemma="рівень" tags="noun:inanim:m:v_naz" />
  <token value="аміаку" lemma="аміак" tags="noun:inanim:m:v_rod" />
  <token value="." lemma="." tags="punct" />
</sentence>
<sentence>
  <token value="Велике" lemma="великий" tags="adj:n:v_zna:compb" />
  <token value="значення" lemma="значення" tags="noun:inanim:n:v_zna" />
  <token value="має" lemma="мати" tags="verb:imperf:pres:s:3" />
  <token value="оптимальний" lemma="оптимальний" tags="adj:m:v_naz:compb" />
  <token value="менеджмент" lemma="менеджмент" tags="noun:inanim:m:v_naz" />
  <token value="і" lemma="і" tags="conj:coord" />
  <token value="правильний" lemma="правильний" tags="adj:m:v_naz:compb" />
  <token value="підбір" lemma="підбір" tags="noun:inanim:m:v_naz" />
  <token value="корму" lemma="корм" tags="noun:inanim:m:v_rod" />
  <token value="." lemma="." tags="punct" />
</sentence>
<sentence>
  <token value="Здоров'я" lemma="здоров'я" tags="noun:inanim:n:v_naz" />
  <token value="кишківника" lemma="кишківник" tags="noun:inanim:m:v_rod" />
  <token value="відіграє" lemma="відігравати" tags="verb:imperf:pres:s:3" />
  <token value="головну" lemma="головний" tags="adj:f:v_zna:compb" />
  <token value="роль" lemma="роль" tags="noun:inanim:f:v_zna" />
  <token value="у" lemma="у" tags="prep" />
  <token value="поліпшенні" lemma="поліпшення" tags="noun:inanim:n:v_mis" />
  <token value="стану" lemma="стан" tags="noun:inanim:m:v_rod:xp2" />
  <token value="підстилки" lemma="підстилка" tags="noun:inanim:f:v_rod" />
  <token value="." lemma="." tags="punct" />
</sentence>
<sentence>
  <token value="Сангровіт" lemma="Сангровіт" tags="noun:inanim:m:v_naz" />
  <token value="допомагає" lemma="допомагати" tags="verb:imperf:pres:s:3" />
  <token value="поліпшити" lemma="поліпшити" tags="verb:perf:inf" />
  <token value="здоров'я" lemma="здоров'я" tags="noun:inanim:n:v_zna" />
  <token value="кишківника" lemma="кишківник" tags="noun:inanim:m:v_rod" />
  <token value="," lemma="," tags="punct" />
  <token value="а" lemma="а" tags="conj:coord" />
  <token value="отже" lemma="отже" tags="conj:subord:&amp;insert" />
  <token value="," lemma="," tags="punct" />
  <token value="і" lemma="і" tags="part" />
  <token value="стан" lemma="стан" tags="noun:inanim:m:v_zna:xp2" />
  <token value="підстилки" lemma="підстилка" tags="noun:inanim:f:v_rod" />
  <token value="," lemma="," tags="punct" />
  <token value="тим" lemma="те" tags="noun:inanim:n:v_oru:&amp;pron:dem" />
  <token value="самим" lemma="самий" tags="adj:n:v_oru:&amp;pron:def" />
  <token value="проявляючи" lemma="проявляючи" tags="advp:imperf" />
  <token value="позитивний" lemma="позитивний" tags="adj:m:v_zna:rinanim:compb" />
  <token value="вплив" lemma="вплив" tags="noun:inanim:m:v_zna" />
  <token value="на" lemma="на" tags="prep" />
  <token value="вирощування" lemma="вирощування" tags="noun:inanim:n:v_zna" />
  <token value="бройлерів" lemma="бройлер" tags="noun:anim:p:v_rod" />
  <token value="." lemma="." tags="punct" />
</sentence>
</text>
